aie2e/__init__.py
aie2e/browser_test_runner.py
aie2e/constants.py
aie2e/mcp_server.py
aie2e/test_models.py
aie2e-0.1.3.dist-info/licenses/LICENSE
aie2e-0.1.3.dist-info/METADATA
aie2e-0.1.3.dist-info/WHEEL
aie2e-0.1.3.dist-info/entry_points.txt
aie2e-0.1.3.dist-info/top_level.txt
aie2e-0.1.3.dist-info/RECORD
