Metadata-Version: 2.4
Name: aie2e
Version: 0.1.3
Summary: AI End-to-End Testing Framework Server
Author-email: AIE2E Team <team@aie2e.dev>
License-Expression: MIT
Project-URL: Homepage, https://github.com/aie2e/aie2e
Project-URL: Repository, https://github.com/aie2e/aie2e.git
Project-URL: Issues, https://github.com/aie2e/aie2e/issues
Keywords: ai,testing,e2e,automation,browser
Classifier: Development Status :: 3 - Alpha
Classifier: Intended Audience :: Developers
Classifier: Operating System :: OS Independent
Classifier: Programming Language :: Python :: 3
Classifier: Programming Language :: Python :: 3.11
Classifier: Programming Language :: Python :: 3.12
Classifier: Topic :: Software Development :: Testing
Classifier: Topic :: Internet :: WWW/HTTP :: Browsers
Requires-Python: >=3.11
License-File: LICENSE
Requires-Dist: pydantic>=2.11.7
Requires-Dist: pydantic-core>=2.33.2
Requires-Dist: browser-use>=0.5.11
Requires-Dist: fastmcp>=2.12.3
Requires-Dist: uvicorn[standard]>=0.35.0
Requires-Dist: starlette>=0.27
Dynamic: license-file
